Wallace.v
module HA(a,b,sum,carry);
input a,b;
output sum,carry;
assign sum=a^b;
assign carry=a&b;
endmodule



module FA(a,b,cin,sum,carry);
input a,b,cin;
output sum,carry;
wire T1,T2,T3;
xor(sum,a,b,cin);
and(T1,a,b);
and(T2,a,cin);
and(T3,b,cin);
or(carry,T3,T2,T1);
endmodule


`timescale 1ns / 1ps

module wallace1(output reg [7:0] product, input [7:0] x, y, input clock);

reg p [7:0][7:0];

wire [21:1] fs ,fc;

wire [10:1] hs, hc;

integer i,j;

always@(y, x)

begin

for ( i = 0; i <= 7; i = i + 1)

for ( j = 0; i + j <= 7; j = j + 1)

p[i][j] <= x[i] & y[j];

end
///////////////////////////////////////////////////////////////////////////////////
HA ha_1 ( .sum(hs[1]), .carry(hc[1]), .a(p[1][0]), .b( p[0][1]));

FA fa_1 ( .sum(fs[1]), .carry(fc[1]), .a(p[2][0]), .b( p[1][1]), .cin( p[0][2] ) );

FA fa_2 ( .sum(fs[2]), .carry(fc[2]), .a(p[2][1]), .b( p[0][3]), .cin( p[1][2] ) );

FA fa_3 ( .sum(fs[3]), .carry(fc[3]), .a(p[0][4]), .b( p[1][3]), .cin( p[2][2] ) );

HA ha_2 ( .sum(hs[2]), .carry(hc[2]), .a(p[3][1]), .b( p[4][0]));

FA fa_4 ( .sum(fs[4]), .carry(fc[4]), .a(p[0][5]), .b( p[1][4]), .cin( p[2][3] ) );

FA fa_5 ( .sum(fs[5]), .carry(fc[5]), .a(p[3][2]), .b( p[4][1]), .cin( p[5][0] ) );

FA fa_6 ( .sum(fs[6]), .carry(fc[6]), .a(p[0][6]), .b( p[1][5]), .cin( p[2][4] ) );

FA fa_7 ( .sum(fs[7]), .carry(fc[7]), .a(p[3][3]), .b( p[4][2]), .cin( p[5][1] ) );

FA fa_8 ( .sum(fs[8]), .carry(fc[8]), .a(p[0][7]), .b( p[1][6]), .cin( p[2][5] ) );

FA fa_9 ( .sum(fs[9]), .carry(fc[9]), .a(p[3][4]), .b( p[4][3]), .cin( p[5][2] ) );
///////////////////////////////////////////////////////////////////////////////////
HA ha_3 ( .sum(hs[3]), .carry(hc[3]), .a(hc[1]), .b( fs[1]));

FA fa_10 ( .sum(fs[10]), .carry(fc[10]), .a(fc[1]), .b( fs[2]), .cin( p[3][0] ) );

FA fa_11 ( .sum(fs[11]), .carry(fc[11]), .a(fc[2]), .b( fs[3]), .cin( hs[2] ) );

FA fa_12 ( .sum(fs[12]), .carry(fc[12]), .a(fc[3]), .b( hc[2]), .cin( fs[4] ) );

FA fa_13 ( .sum(fs[13]), .carry(fc[13]), .a(fc[4]), .b( fc[5]), .cin( fs[6] ) );

HA ha_4 ( .sum(hs[4]), .carry(hc[4]), .a(fs[7]), .b( p[6][0]));

FA fa_14 ( .sum(fs[14]), .carry(fc[14]), .a(fc[6]), .b( fc[7]), .cin( fs[8] ) );

FA fa_15 ( .sum(fs[15]), .carry(fc[15]), .a(fs[9]), .b( p[6][1]), .cin( p[7][0] ) );
///////////////////////////////////////////////////////////////////////////////////
HA ha_5 ( .sum(hs[5]), .carry(hc[5]), .a(hc[3]), .b( fs[10]));

HA ha_6 ( .sum(hs[6]), .carry(hc[6]), .a(fc[10]), .b( fs[11]));

FA fa_16 ( .sum(fs[16]), .carry(fc[16]), .a(fc[11]), .b( fs[12]), .cin( fs[5] ) );

FA fa_17 ( .sum(fs[17]), .carry(fc[17]), .a(fc[12]), .b( fs[13]), .cin( hs[4] ) );

FA fa_18 ( .sum(fs[18]), .carry(fc[18]), .a(fc[13]), .b( hc[4]), .cin( fs[14] ) );
///////////////////////////////////////////////////////////////////////////////////
HA ha_7 ( .sum(hs[7]), .carry(hc[7]), .a(hc[5]), .b( hs[6]));

HA ha_8 ( .sum(hs[8]), .carry(hc[8]), .a(hc[6]), .b( fs[16]));

HA ha_9 ( .sum(hs[9]), .carry(hc[9]), .a(fc[16]), .b( fs[17]));

FA fa_19 ( .sum(fs[19]), .carry(fc[19]), .a(fc[17]), .b( fs[18]), .cin( fs[15] ) );
///////////////////////////////////////////////////////////////////////////////////
HA ha_10 ( .sum(hs[10]), .carry(hc[10]), .a(hc[7]), .b( hs[8]));

FA fa_20 ( .sum(fs[20]), .carry(fc[20]), .a(hc[10]), .b( hc[8]), .cin( hs[9] ) );

FA fa_21 ( .sum(fs[21]), .carry(fc[21]), .a(fc[20]), .b( hc[9]), .cin( fs[19] ) );



always@(posedge clock)
begin

product <={fs[21],fs[20],hs[10],hs[7],hs[5],hs[3],hs[1],p[0][0]};
end

endmodule

module testbench;
 
 reg clock;
 reg [7:0]x;
 reg [7:0]y;
 wire [7:0]product;
 wallace1 wall(product,x,y,clock);

 initial 
    begin
        clock = 1'b0;
        x = 8'b11111110;
        y = 8'b00000110;
    end
always 
    #1 clock = ~clock;

initial
    begin
        #6 x = 8'b00000110;
        #0 y = 8'b00000110;
        #6 x = 8'b00000100;
        #6 x = 8'b00000101;
        #0 y = 8'b11111111;
        #6 x = 8'b00000000;
        #6 x = 8'b00000001;
        #0 y = 8'b00000010;
        #6 $finish;
    end
initial 
    begin
        $dumpfile("wallace.vcd");
        $dumpvars;
    end


endmodule

wallace.vcd
$date
	Fri Oct 18 16:50:52 2019
$end
$version
	Icarus Verilog
$end
$timescale
	1ps
$end
$scope module testbench $end
$var wire 8 ! product [7:0] $end
$var reg 1 " clock $end
$var reg 8 # x [7:0] $end
$var reg 8 $ y [7:0] $end
$scope module wall $end
$var wire 1 " clock $end
$var wire 8 % x [7:0] $end
$var wire 8 & y [7:0] $end
$var wire 10 ' hs [10:1] $end
$var wire 10 ( hc [10:1] $end
$var wire 21 ) fs [21:1] $end
$var wire 21 * fc [21:1] $end
$var reg 8 + product [7:0] $end
$var integer 32 , i [31:0] $end
$var integer 32 - j [31:0] $end
$scope module fa_1 $end
$var wire 1 . T1 $end
$var wire 1 / T2 $end
$var wire 1 0 T3 $end
$var wire 1 1 a $end
$var wire 1 2 b $end
$var wire 1 3 carry $end
$var wire 1 4 cin $end
$var wire 1 5 sum $end
$upscope $end
$scope module fa_10 $end
$var wire 1 6 T1 $end
$var wire 1 7 T2 $end
$var wire 1 8 T3 $end
$var wire 1 9 a $end
$var wire 1 : b $end
$var wire 1 ; carry $end
$var wire 1 < cin $end
$var wire 1 = sum $end
$upscope $end
$scope module fa_11 $end
$var wire 1 > T1 $end
$var wire 1 ? T2 $end
$var wire 1 @ T3 $end
$var wire 1 A a $end
$var wire 1 B b $end
$var wire 1 C carry $end
$var wire 1 D cin $end
$var wire 1 E sum $end
$upscope $end
$scope module fa_12 $end
$var wire 1 F T1 $end
$var wire 1 G T2 $end
$var wire 1 H T3 $end
$var wire 1 I a $end
$var wire 1 J b $end
$var wire 1 K carry $end
$var wire 1 L cin $end
$var wire 1 M sum $end
$upscope $end
$scope module fa_13 $end
$var wire 1 N T1 $end
$var wire 1 O T2 $end
$var wire 1 P T3 $end
$var wire 1 Q a $end
$var wire 1 R b $end
$var wire 1 S carry $end
$var wire 1 T cin $end
$var wire 1 U sum $end
$upscope $end
$scope module fa_14 $end
$var wire 1 V T1 $end
$var wire 1 W T2 $end
$var wire 1 X T3 $end
$var wire 1 Y a $end
$var wire 1 Z b $end
$var wire 1 [ carry $end
$var wire 1 \ cin $end
$var wire 1 ] sum $end
$upscope $end
$scope module fa_15 $end
$var wire 1 ^ T1 $end
$var wire 1 _ T2 $end
$var wire 1 ` T3 $end
$var wire 1 a a $end
$var wire 1 b b $end
$var wire 1 c carry $end
$var wire 1 d cin $end
$var wire 1 e sum $end
$upscope $end
$scope module fa_16 $end
$var wire 1 f T1 $end
$var wire 1 g T2 $end
$var wire 1 h T3 $end
$var wire 1 i a $end
$var wire 1 j b $end
$var wire 1 k carry $end
$var wire 1 l cin $end
$var wire 1 m sum $end
$upscope $end
$scope module fa_17 $end
$var wire 1 n T1 $end
$var wire 1 o T2 $end
$var wire 1 p T3 $end
$var wire 1 q a $end
$var wire 1 r b $end
$var wire 1 s carry $end
$var wire 1 t cin $end
$var wire 1 u sum $end
$upscope $end
$scope module fa_18 $end
$var wire 1 v T1 $end
$var wire 1 w T2 $end
$var wire 1 x T3 $end
$var wire 1 y a $end
$var wire 1 z b $end
$var wire 1 { carry $end
$var wire 1 | cin $end
$var wire 1 } sum $end
$upscope $end
$scope module fa_19 $end
$var wire 1 ~ T1 $end
$var wire 1 !" T2 $end
$var wire 1 "" T3 $end
$var wire 1 #" a $end
$var wire 1 $" b $end
$var wire 1 %" carry $end
$var wire 1 &" cin $end
$var wire 1 '" sum $end
$upscope $end
$scope module fa_2 $end
$var wire 1 (" T1 $end
$var wire 1 )" T2 $end
$var wire 1 *" T3 $end
$var wire 1 +" a $end
$var wire 1 ," b $end
$var wire 1 -" carry $end
$var wire 1 ." cin $end
$var wire 1 /" sum $end
$upscope $end
$scope module fa_20 $end
$var wire 1 0" T1 $end
$var wire 1 1" T2 $end
$var wire 1 2" T3 $end
$var wire 1 3" a $end
$var wire 1 4" b $end
$var wire 1 5" carry $end
$var wire 1 6" cin $end
$var wire 1 7" sum $end
$upscope $end
$scope module fa_21 $end
$var wire 1 8" T1 $end
$var wire 1 9" T2 $end
$var wire 1 :" T3 $end
$var wire 1 ;" a $end
$var wire 1 <" b $end
$var wire 1 =" carry $end
$var wire 1 >" cin $end
$var wire 1 ?" sum $end
$upscope $end
$scope module fa_3 $end
$var wire 1 @" T1 $end
$var wire 1 A" T2 $end
$var wire 1 B" T3 $end
$var wire 1 C" a $end
$var wire 1 D" b $end
$var wire 1 E" carry $end
$var wire 1 F" cin $end
$var wire 1 G" sum $end
$upscope $end
$scope module fa_4 $end
$var wire 1 H" T1 $end
$var wire 1 I" T2 $end
$var wire 1 J" T3 $end
$var wire 1 K" a $end
$var wire 1 L" b $end
$var wire 1 M" carry $end
$var wire 1 N" cin $end
$var wire 1 O" sum $end
$upscope $end
$scope module fa_5 $end
$var wire 1 P" T1 $end
$var wire 1 Q" T2 $end
$var wire 1 R" T3 $end
$var wire 1 S" a $end
$var wire 1 T" b $end
$var wire 1 U" carry $end
$var wire 1 V" cin $end
$var wire 1 W" sum $end
$upscope $end
$scope module fa_6 $end
$var wire 1 X" T1 $end
$var wire 1 Y" T2 $end
$var wire 1 Z" T3 $end
$var wire 1 [" a $end
$var wire 1 \" b $end
$var wire 1 ]" carry $end
$var wire 1 ^" cin $end
$var wire 1 _" sum $end
$upscope $end
$scope module fa_7 $end
$var wire 1 `" T1 $end
$var wire 1 a" T2 $end
$var wire 1 b" T3 $end
$var wire 1 c" a $end
$var wire 1 d" b $end
$var wire 1 e" carry $end
$var wire 1 f" cin $end
$var wire 1 g" sum $end
$upscope $end
$scope module fa_8 $end
$var wire 1 h" T1 $end
$var wire 1 i" T2 $end
$var wire 1 j" T3 $end
$var wire 1 k" a $end
$var wire 1 l" b $end
$var wire 1 m" carry $end
$var wire 1 n" cin $end
$var wire 1 o" sum $end
$upscope $end
$scope module fa_9 $end
$var wire 1 p" T1 $end
$var wire 1 q" T2 $end
$var wire 1 r" T3 $end
$var wire 1 s" a $end
$var wire 1 t" b $end
$var wire 1 u" carry $end
$var wire 1 v" cin $end
$var wire 1 w" sum $end
$upscope $end
$scope module ha_1 $end
$var wire 1 x" a $end
$var wire 1 y" b $end
$var wire 1 z" carry $end
$var wire 1 {" sum $end
$upscope $end
$scope module ha_10 $end
$var wire 1 |" a $end
$var wire 1 }" b $end
$var wire 1 ~" carry $end
$var wire 1 !# sum $end
$upscope $end
$scope module ha_2 $end
$var wire 1 "# a $end
$var wire 1 ## b $end
$var wire 1 $# carry $end
$var wire 1 %# sum $end
$upscope $end
$scope module ha_3 $end
$var wire 1 &# a $end
$var wire 1 '# b $end
$var wire 1 (# carry $end
$var wire 1 )# sum $end
$upscope $end
$scope module ha_4 $end
$var wire 1 *# a $end
$var wire 1 +# b $end
$var wire 1 ,# carry $end
$var wire 1 -# sum $end
$upscope $end
$scope module ha_5 $end
$var wire 1 .# a $end
$var wire 1 /# b $end
$var wire 1 0# carry $end
$var wire 1 1# sum $end
$upscope $end
$scope module ha_6 $end
$var wire 1 2# a $end
$var wire 1 3# b $end
$var wire 1 4# carry $end
$var wire 1 5# sum $end
$upscope $end
$scope module ha_7 $end
$var wire 1 6# a $end
$var wire 1 7# b $end
$var wire 1 8# carry $end
$var wire 1 9# sum $end
$upscope $end
$scope module ha_8 $end
$var wire 1 :# a $end
$var wire 1 ;# b $end
$var wire 1 <# carry $end
$var wire 1 =# sum $end
$upscope $end
$scope module ha_9 $end
$var wire 1 ># a $end
$var wire 1 ?# b $end
$var wire 1 @# carry $end
$var wire 1 A# sum $end
$upscope $end
$upscope $end
$upscope $end
$enddefinitions $end
#0
$dumpvars
1A#
0@#
1?#
0>#
1=#
0<#
1;#
0:#
19#
08#
17#
06#
15#
04#
13#
02#
01#
00#
0/#
0.#
0-#
0,#
0+#
0*#
1)#
0(#
1'#
0&#
1%#
0$#
0##
1"#
1!#
0~"
1}"
0|"
0{"
0z"
0y"
0x"
1w"
1v"
0u"
0t"
0s"
0r"
0q"
0p"
0o"
0n"
0m"
0l"
0k"
0j"
0i"
0h"
0g"
1f"
1e"
1d"
0c"
1b"
0a"
0`"
0_"
0^"
0]"
0\"
0["
0Z"
0Y"
0X"
0W"
0V"
1U"
1T"
1S"
0R"
0Q"
1P"
0O"
0N"
0M"
0L"
0K"
0J"
0I"
0H"
1G"
1F"
0E"
0D"
0C"
0B"
0A"
0@"
1?"
1>"
0="
0<"
0;"
0:"
09"
08"
17"
16"
05"
04"
03"
02"
01"
00"
0/"
1."
1-"
0,"
1+"
0*"
1)"
0("
1'"
0&"
0%"
1$"
0#"
0""
0!"
0~
1}
1|
0{
0z
0y
0x
0w
0v
1u
0t
0s
1r
0q
0p
0o
0n
1m
0l
0k
0j
1i
0h
0g
0f
0e
0d
1c
1b
1a
0`
0_
1^
1]
0\
0[
1Z
0Y
0X
0W
0V
1U
0T
0S
1R
0Q
0P
0O
0N
0M
0L
0K
0J
0I
0H
0G
0F
1E
1D
1C
1B
1A
1@
1?
1>
0=
0<
0;
0:
09
08
07
06
15
04
03
12
01
00
0/
0.
b1 -
b1000 ,
bx +
b100010001010010 *
b111111011010100000101 )
b0 (
b1111100110 '
b110 &
b11111110 %
b110 $
b11111110 #
0"
bx !
$end
#1000
b11110100 !
b11110100 +
1"
#2000
0"
#3000
1"
#4000
0"
#5000
1"
#6000
07"
06"
0A#
0$"
0?#
09#
0}
0u
07#
0?"
0|
0r
05#
0>"
0%"
0]
0U
03#
0'"
0""
0Z
0R
0E
0?
0@
0&"
0c
0a
0e"
b10000000010 *
0U"
0D
0e
0^
b1000000000000101 )
0w"
0b"
0P"
b1010000100 '
0%#
0b
0v"
0f"
0d"
0T"
0S"
0"#
b1 -
b1000 ,
0"
b110 #
b110 %
#7000
b100100 !
b100100 +
1"
#8000
0"
#9000
1"
#10000
0"
#11000
1"
#12000
0!#
0}"
0=#
19#
0;#
17#
0m
15#
0i
11#
13#
0C
1/#
1E
0>
1=
0A
b1110000 '
0)#
1:
b0 *
0-"
0'#
1/"
0)"
b11000000110 )
05
0."
02
b1 -
b1000 ,
0"
b100 #
b100 %
#13000
b11000 !
b11000 +
1"
#14000
0"
#15000
1"
#16000
0"
#17000
1"
#18000
1?"
17"
1!#
1>"
16"
1}"
1'"
1A#
1=#
1$"
1?#
1;#
1}
1u
1m
1|
1r
1j
1]
1U
1M
1Y
1Q
1I
1A
19
1m"
1]"
1M"
0B
1E"
0:
1-"
b10101111 *
13
1i"
1Y"
1I"
0G"
1A"
b111111011111000000000 )
0/"
1("
1/
b1111110001 '
1{"
1n"
1^"
1N"
11
1k"
1["
1K"
1C"
1,"
14
1y"
b11111111 $
b11111111 &
b1 -
b1000 ,
0"
b101 #
b101 %
#19000
b11111011 !
b11111011 +
1"
#20000
0"
#21000
1"
#22000
0"
#23000
1"
#24000
0?"
07"
0!#
0>"
06"
0}"
0'"
0A#
0=#
09#
0$"
0?#
0;#
07#
0}
0u
0m
05#
01#
0|
0r
0j
03#
0/#
0]
0U
0M
0E
b0 )
0=
0Y
0Q
0I
0A
09
0m"
0]"
0M"
0E"
0-"
b0 *
03
0i"
0Y"
0I"
0A"
0("
0/
b0 '
0{"
0n"
0^"
0N"
0F"
0+"
01
0k"
0["
0K"
0C"
0,"
04
0y"
b1 -
b1000 ,
0"
b0 #
b0 %
#25000
b0 !
b0 +
1"
#26000
0"
#27000
1"
#28000
0"
#29000
1"
#30000
b1 '
1{"
0k"
0["
0K"
0C"
0,"
04
1y"
b10 $
b10 &
b1 -
b1000 ,
0"
b1 #
b1 %
#31000
b10 !
b10 +
1"
